langchain_modelscope/__init__.py
langchain_modelscope/chat_models.py
langchain_modelscope/embeddings.py
langchain_modelscope/llms.py
langchain_modelscope/py.typed
langchain_modelscope_integration-0.1.1.dist-info/LICENSE
langchain_modelscope_integration-0.1.1.dist-info/METADATA
langchain_modelscope_integration-0.1.1.dist-info/WHEEL
langchain_modelscope_integration-0.1.1.dist-info/RECORD
