Metadata-Version: 2.3
Name: langchain-modelscope-integration
Version: 0.1.1
Summary: An integration package connecting ModelScope and LangChain
License: Apache-2.0
Requires-Python: >=3.9,<4.0
Classifier: License :: OSI Approved :: Apache Software License
Classifier: Programming Language :: Python :: 3
Classifier: Programming Language :: Python :: 3.9
Classifier: Programming Language :: Python :: 3.10
Classifier: Programming Language :: Python :: 3.11
Classifier: Programming Language :: Python :: 3.12
Classifier: Programming Language :: Python :: 3.13
Requires-Dist: langchain-core (>=0.3.15,<0.4.0)
Requires-Dist: langchain-openai (>=0.2.14,<0.3.0)
Requires-Dist: modelscope (>=1.21.0,<2.0.0)
Requires-Dist: openai (>=1.58.1,<2.0.0)
Project-URL: Repository, https://github.com/modelscope/langchain-modelscope
Project-URL: Release Notes, https://github.com/langchain-ai/langchain/releases?q=tag%3A%22modelscope%3D%3D0%22&expanded=true
Project-URL: Source Code, https://github.com/langchain-ai/langchain/tree/master/libs/partners/modelscope
